llm_factory/__init__.py
llm_factory/factory.py
process_gpt_llm_factory-1.0.2.dist-info/licenses/LICENSE
process_gpt_llm_factory-1.0.2.dist-info/METADATA
process_gpt_llm_factory-1.0.2.dist-info/WHEEL
process_gpt_llm_factory-1.0.2.dist-info/top_level.txt
process_gpt_llm_factory-1.0.2.dist-info/RECORD
