Metadata-Version: 2.4
Name: process-gpt-llm-factory
Version: 1.0.2
Summary: 통합 LLM 팩토리 라이브러리 - 다양한 LLM 제공자를 통합된 인터페이스로 사용
Home-page: https://github.com/yourusername/llm-factory
Author: Your Name
Author-email: Your Name <your.email@example.com>
License: MIT
Project-URL: Homepage, https://github.com/yourusername/llm-factory
Project-URL: Repository, https://github.com/yourusername/llm-factory
Project-URL: Documentation, https://github.com/yourusername/llm-factory#readme
Project-URL: Bug Tracker, https://github.com/yourusername/llm-factory/issues
Keywords: llm,openai,azure,anthropic,ollama,langchain,factory,ai
Classifier: Development Status :: 4 - Beta
Classifier: Intended Audience :: Developers
Classifier: License :: OSI Approved :: MIT License
Classifier: Operating System :: OS Independent
Classifier: Programming Language :: Python :: 3
Classifier: Programming Language :: Python :: 3.8
Classifier: Programming Language :: Python :: 3.9
Classifier: Programming Language :: Python :: 3.10
Classifier: Programming Language :: Python :: 3.11
Classifier: Programming Language :: Python :: 3.12
Classifier: Topic :: Software Development :: Libraries :: Python Modules
Classifier: Topic :: Scientific/Engineering :: Artificial Intelligence
Requires-Python: >=3.8
License-File: LICENSE
Requires-Dist: langchain<0.4.0,>=0.2.0
Requires-Dist: langchain-openai<0.3.0,>=0.2.1
Requires-Dist: langchain-core<0.4.0,>=0.2.0
Requires-Dist: langchain-anthropic<0.4.0,>=0.1.0
Requires-Dist: langchain-ollama<0.4.0,>=0.1.0
Requires-Dist: python-dotenv>=1.0.0
Provides-Extra: dev
Requires-Dist: pytest>=7.0.0; extra == "dev"
Requires-Dist: pytest-asyncio>=0.21.0; extra == "dev"
Requires-Dist: black>=23.0.0; extra == "dev"
Requires-Dist: isort>=5.12.0; extra == "dev"
Requires-Dist: flake8>=6.0.0; extra == "dev"
Requires-Dist: mypy>=1.0.0; extra == "dev"
Dynamic: author
Dynamic: home-page
Dynamic: license-file
Dynamic: requires-python
